test_port_gun/__init__.py
test_port_gun/__main__.py
test_port_gun/main.py
test_port_gun-0.1.0.dist-info/METADATA
test_port_gun-0.1.0.dist-info/WHEEL
test_port_gun-0.1.0.dist-info/entry_points.txt
test_port_gun-0.1.0.dist-info/RECORD
