Metadata-Version: 2.1
Name: test-port-gun
Version: 0.1.0
Summary: 
Author: danprince8984
Author-email: danprince8984@gmail.com
Requires-Python: >=3.8,<4.0
Classifier: Programming Language :: Python :: 3
Classifier: Programming Language :: Python :: 3.8
Classifier: Programming Language :: Python :: 3.9
Classifier: Programming Language :: Python :: 3.10
Classifier: Programming Language :: Python :: 3.11
Requires-Dist: typer[all] (>=0.7.0,<0.8.0)
